{
    "Device 1": {
        "Company": "CHONGQING FUGUI ELECTRONICS CO.,LTD.",
        "Username": "admin",
        "Password": "",
        "PasswordChanged": false,
        "flagged": false
    },
    "Device 2": {
        "Company": "Intel Corporate",
        "Username": "admin",
        "Password": "",
        "PasswordChanged": false,
        "flagged": false
    },
    "Device 3": {
        "Company": "Apple, Inc.",
        "Username": "admin",
        "Password": "",
        "PasswordChanged": false,
        "flagged": false
    },
    "Device 4": {
        "Company": "Intel Corporate",
        "Username": "admin",
        "Password": "",
        "PasswordChanged": false,
        "flagged": false
    },
    "Device 5": {
        "Company": "Apple, Inc.",
        "Username": "admin",
        "Password": "",
        "PasswordChanged": false,
        "flagged": false
    },
    "Device 6": {
        "Company": "Intel Corporate",
        "Username": "admin",
        "Password": "",
        "PasswordChanged": false,
        "flagged": false
    },
    "Device 7": {
        "Company": "*NO COMPANY*",
        "Username": "admin",
        "Password": "",
        "PasswordChanged": false,
        "flagged": false
    },
    "Device 8": {
        "Company": "CLOUD NETWORK TECHNOLOGY SINGAPORE PTE. LTD.",
        "Username": "admin",
        "Password": "",
        "PasswordChanged": false,
        "flagged": false
    },
    "Device 9": {
        "Company": "TP-Link Corporation Limited",
        "Username": "admin",
        "Password": "",
        "PasswordChanged": false,
        "flagged": false
    },
    "Device 10": {
        "Company": "*NO COMPANY*",
        "Username": "admin",
        "Password": "",
        "PasswordChanged": false,
        "flagged": false
    },
    "Device 11": {
        "Company": "*NO COMPANY*",
        "Username": "admin",
        "Password": "",
        "PasswordChanged": false,
        "flagged": false
    },
    "Device 12": {
        "Company": "*NO COMPANY*",
        "Username": "admin",
        "Password": "",
        "PasswordChanged": false,
        "flagged": false
    },
    "Device 13": {
        "Company": "Intel Corporate",
        "Username": "admin",
        "Password": "",
        "PasswordChanged": false,
        "flagged": false
    },
    "Device 14": {
        "Company": "*NO COMPANY*",
        "Username": "admin",
        "Password": "",
        "PasswordChanged": false,
        "flagged": false
    },
    "Device 15": {
        "Company": "*NO COMPANY*",
        "Username": "admin",
        "Password": "",
        "PasswordChanged": false,
        "flagged": false
    },
    "Device 16": {
        "Company": "*NO COMPANY*",
        "Username": "admin",
        "Password": "",
        "PasswordChanged": false,
        "flagged": false
    },
    "Device 17": {
        "Company": "*NO COMPANY*",
        "Username": "admin",
        "Password": "",
        "PasswordChanged": false,
        "flagged": false
    },
    "Device 18": {
        "Company": "Intel Corporate",
        "Username": "admin",
        "Password": "",
        "PasswordChanged": false,
        "flagged": false
    },
    "Device 19": {
        "Company": "Intel Corporate",
        "Username": "admin",
        "Password": "",
        "PasswordChanged": false,
        "flagged": false
    },
    "Device 20": {
        "Company": "*NO COMPANY*",
        "Username": "admin",
        "Password": "",
        "PasswordChanged": false,
        "flagged": false
    },
    "Device 21": {
        "Company": "*NO COMPANY*",
        "Username": "admin",
        "Password": "",
        "PasswordChanged": false,
        "flagged": false
    },
    "Device 22": {
        "Company": "*NO COMPANY*",
        "Username": "admin",
        "Password": "",
        "PasswordChanged": false,
        "flagged": false
    },
    "Device 23": {
        "Company": "AMPAK Technology,Inc.",
        "Username": "admin",
        "Password": "",
        "PasswordChanged": false,
        "flagged": false
    },
    "Device 24": {
        "Company": "*NO COMPANY*",
        "Username": "admin",
        "Password": "",
        "PasswordChanged": false,
        "flagged": false
    },
    "Device 25": {
        "Company": "*NO COMPANY*",
        "Username": "admin",
        "Password": "",
        "PasswordChanged": false,
        "flagged": false
    },
    "Device 26": {
        "Company": "*NO COMPANY*",
        "Username": "admin",
        "Password": "",
        "PasswordChanged": false,
        "flagged": false
    },
    "Device 27": {
        "Company": "*NO COMPANY*",
        "Username": "admin",
        "Password": "",
        "PasswordChanged": false,
        "flagged": false
    },
    "Device 28": {
        "Company": "*NO COMPANY*",
        "Username": "admin",
        "Password": "",
        "PasswordChanged": false,
        "flagged": false
    },
    "Device 29": {
        "Company": "*NO COMPANY*",
        "Username": "admin",
        "Password": "",
        "PasswordChanged": false,
        "flagged": false
    },
    "Device 30": {
        "Company": "*NO COMPANY*",
        "Username": "admin",
        "Password": "",
        "PasswordChanged": false,
        "flagged": false
    },
    "Device 31": {
        "Company": "*NO COMPANY*",
        "Username": "admin",
        "Password": "",
        "PasswordChanged": false,
        "flagged": false
    },
    "Device 32": {
        "Company": "*NO COMPANY*",
        "Username": "admin",
        "Password": "",
        "PasswordChanged": false,
        "flagged": false
    },
    "Device 33": {
        "Company": "*NO COMPANY*",
        "Username": "admin",
        "Password": "",
        "PasswordChanged": false,
        "flagged": false
    },
    "Device 34": {
        "Company": "*NO COMPANY*",
        "Username": "admin",
        "Password": "",
        "PasswordChanged": false,
        "flagged": false
    },
    "Device 35": {
        "Company": "*NO COMPANY*",
        "Username": "admin",
        "Password": "",
        "PasswordChanged": false,
        "flagged": false
    },
    "Device 36": {
        "Company": "Intel Corporate",
        "Username": "admin",
        "Password": "",
        "PasswordChanged": false,
        "flagged": false
    },
    "Device 37": {
        "Company": "*NO COMPANY*",
        "Username": "admin",
        "Password": "",
        "PasswordChanged": false,
        "flagged": false
    },
    "Device 38": {
        "Company": "*NO COMPANY*",
        "Username": "admin",
        "Password": "",
        "PasswordChanged": false,
        "flagged": false
    },
    "Device 39": {
        "Company": "*NO COMPANY*",
        "Username": "admin",
        "Password": "",
        "PasswordChanged": false,
        "flagged": false
    },
    "Device 40": {
        "Company": "*NO COMPANY*",
        "Username": "admin",
        "Password": "",
        "PasswordChanged": false,
        "flagged": false
    },
    "Device 41": {
        "Company": "Intel Corporate",
        "Username": "admin",
        "Password": "",
        "PasswordChanged": false,
        "flagged": false
    },
    "Device 42": {
        "Company": "Sony Interactive Entertainment Inc.",
        "Username": "admin",
        "Password": "",
        "PasswordChanged": false,
        "flagged": false
    },
    "Device 43": {
        "Company": "*NO COMPANY*",
        "Username": "admin",
        "Password": "",
        "PasswordChanged": false,
        "flagged": false
    },
    "Device 44": {
        "Company": "*NO COMPANY*",
        "Username": "admin",
        "Password": "",
        "PasswordChanged": false,
        "flagged": false
    },
    "Device 45": {
        "Company": "*NO COMPANY*",
        "Username": "admin",
        "Password": "",
        "PasswordChanged": false,
        "flagged": false
    },
    "Device 46": {
        "Company": "*NO COMPANY*",
        "Username": "admin",
        "Password": "",
        "PasswordChanged": false,
        "flagged": false
    },
    "Device 47": {
        "Company": "Apple, Inc.",
        "Username": "admin",
        "Password": "",
        "PasswordChanged": false,
        "flagged": false
    },
    "Device 48": {
        "Company": "*NO COMPANY*",
        "Username": "admin",
        "Password": "",
        "PasswordChanged": false,
        "flagged": false
    },
    "Device 49": {
        "Company": "*NO COMPANY*",
        "Username": "admin",
        "Password": "",
        "PasswordChanged": false,
        "flagged": false
    },
    "Device 50": {
        "Company": "*NO COMPANY*",
        "Username": "admin",
        "Password": "",
        "PasswordChanged": false,
        "flagged": false
    },
    "Device 51": {
        "Company": "*NO COMPANY*",
        "Username": "admin",
        "Password": "",
        "PasswordChanged": false,
        "flagged": false
    },
    "Device 52": {
        "Company": "*NO COMPANY*",
        "Username": "admin",
        "Password": "",
        "PasswordChanged": false,
        "flagged": false
    },
    "Device 53": {
        "Company": "Apple, Inc.",
        "Username": "admin",
        "Password": "",
        "PasswordChanged": false,
        "flagged": false
    },
    "Device 54": {
        "Company": "*NO COMPANY*",
        "Username": "admin",
        "Password": "",
        "PasswordChanged": false,
        "flagged": false
    },
    "Device 55": {
        "Company": "*NO COMPANY*",
        "Username": "admin",
        "Password": "",
        "PasswordChanged": false,
        "flagged": false
    },
    "Device 56": {
        "Company": "*NO COMPANY*",
        "Username": "admin",
        "Password": "",
        "PasswordChanged": false,
        "flagged": false
    },
    "Device 57": {
        "Company": "*NO COMPANY*",
        "Username": "admin",
        "Password": "",
        "PasswordChanged": false,
        "flagged": false
    },
    "Device 58": {
        "Company": "*NO COMPANY*",
        "Username": "admin",
        "Password": "",
        "PasswordChanged": false,
        "flagged": false
    },
    "Device 59": {
        "Company": "*NO COMPANY*",
        "Username": "admin",
        "Password": "",
        "PasswordChanged": false,
        "flagged": false
    },
    "Device 60": {
        "Company": "*NO COMPANY*",
        "Username": "admin",
        "Password": "",
        "PasswordChanged": false,
        "flagged": false
    },
    "Device 61": {
        "Company": "*NO COMPANY*",
        "Username": "admin",
        "Password": "",
        "PasswordChanged": false,
        "flagged": false
    },
    "Device 62": {
        "Company": "Intel Corporate",
        "Username": "admin",
        "Password": "",
        "PasswordChanged": false,
        "flagged": false
    },
    "Device 63": {
        "Company": "*NO COMPANY*",
        "Username": "admin",
        "Password": "",
        "PasswordChanged": false,
        "flagged": false
    },
    "Device 64": {
        "Company": "Intel Corporate",
        "Username": "admin",
        "Password": "",
        "PasswordChanged": false,
        "flagged": false
    },
    "Device 65": {
        "Company": "Intel Corporate",
        "Username": "admin",
        "Password": "",
        "PasswordChanged": false,
        "flagged": false
    },
    "Device 66": {
        "Company": "*NO COMPANY*",
        "Username": "admin",
        "Password": "",
        "PasswordChanged": false,
        "flagged": false
    },
    "Device 67": {
        "Company": "*NO COMPANY*",
        "Username": "admin",
        "Password": "",
        "PasswordChanged": false,
        "flagged": false
    },
    "Device 68": {
        "Company": "CLOUD NETWORK TECHNOLOGY SINGAPORE PTE. LTD.",
        "Username": "admin",
        "Password": "",
        "PasswordChanged": false,
        "flagged": false
    },
    "Device 69": {
        "Company": "*NO COMPANY*",
        "Username": "admin",
        "Password": "",
        "PasswordChanged": false,
        "flagged": false
    },
    "Device 70": {
        "Company": "*NO COMPANY*",
        "Username": "admin",
        "Password": "",
        "PasswordChanged": false,
        "flagged": false
    },
    "Device 71": {
        "Company": "Microsoft",
        "Username": "admin",
        "Password": "",
        "PasswordChanged": false,
        "flagged": false
    },
    "Device 72": {
        "Company": "*NO COMPANY*",
        "Username": "admin",
        "Password": "",
        "PasswordChanged": false,
        "flagged": false
    },
    "Device 73": {
        "Company": "*NO COMPANY*",
        "Username": "admin",
        "Password": "",
        "PasswordChanged": false,
        "flagged": false
    },
    "Device 74": {
        "Company": "*NO COMPANY*",
        "Username": "admin",
        "Password": "",
        "PasswordChanged": false,
        "flagged": false
    },
    "Device 75": {
        "Company": "Intel Corporate",
        "Username": "admin",
        "Password": "",
        "PasswordChanged": false,
        "flagged": false
    },
    "Device 76": {
        "Company": "AzureWave Technology Inc.",
        "Username": "admin",
        "Password": "",
        "PasswordChanged": false,
        "flagged": false
    },
    "Device 77": {
        "Company": "*NO COMPANY*",
        "Username": "admin",
        "Password": "",
        "PasswordChanged": false,
        "flagged": false
    },
    "Device 78": {
        "Company": "*NO COMPANY*",
        "Username": "admin",
        "Password": "",
        "PasswordChanged": false,
        "flagged": false
    },
    "Device 79": {
        "Company": "Apple, Inc.",
        "Username": "admin",
        "Password": "",
        "PasswordChanged": false,
        "flagged": false
    },
    "Device 80": {
        "Company": "*NO COMPANY*",
        "Username": "admin",
        "Password": "",
        "PasswordChanged": false,
        "flagged": false
    },
    "Device 81": {
        "Company": "*NO COMPANY*",
        "Username": "admin",
        "Password": "",
        "PasswordChanged": false,
        "flagged": false
    },
    "Device 82": {
        "Company": "*NO COMPANY*",
        "Username": "admin",
        "Password": "",
        "PasswordChanged": false,
        "flagged": false
    },
    "Device 83": {
        "Company": "Intel Corporate",
        "Username": "admin",
        "Password": "",
        "PasswordChanged": false,
        "flagged": false
    },
    "Device 84": {
        "Company": "*NO COMPANY*",
        "Username": "admin",
        "Password": "",
        "PasswordChanged": false,
        "flagged": false
    },
    "Device 85": {
        "Company": "*NO COMPANY*",
        "Username": "admin",
        "Password": "",
        "PasswordChanged": false,
        "flagged": false
    },
    "Device 86": {
        "Company": "*NO COMPANY*",
        "Username": "admin",
        "Password": "",
        "PasswordChanged": false,
        "flagged": false
    },
    "Device 87": {
        "Company": "*NO COMPANY*",
        "Username": "admin",
        "Password": "",
        "PasswordChanged": false,
        "flagged": false
    },
    "Device 88": {
        "Company": "*NO COMPANY*",
        "Username": "admin",
        "Password": "",
        "PasswordChanged": false,
        "flagged": false
    },
    "Device 89": {
        "Company": "*NO COMPANY*",
        "Username": "admin",
        "Password": "",
        "PasswordChanged": false,
        "flagged": false
    },
    "Device 90": {
        "Company": "*NO COMPANY*",
        "Username": "admin",
        "Password": "",
        "PasswordChanged": false,
        "flagged": false
    },
    "Device 91": {
        "Company": "*NO COMPANY*",
        "Username": "admin",
        "Password": "",
        "PasswordChanged": false,
        "flagged": false
    },
    "Device 92": {
        "Company": "*NO COMPANY*",
        "Username": "admin",
        "Password": "",
        "PasswordChanged": false,
        "flagged": false
    },
    "Device 93": {
        "Company": "*NO COMPANY*",
        "Username": "admin",
        "Password": "",
        "PasswordChanged": false,
        "flagged": false
    },
    "Device 94": {
        "Company": "*NO COMPANY*",
        "Username": "admin",
        "Password": "",
        "PasswordChanged": false,
        "flagged": false
    },
    "Device 95": {
        "Company": "*NO COMPANY*",
        "Username": "admin",
        "Password": "",
        "PasswordChanged": false,
        "flagged": false
    },
    "Device 96": {
        "Company": "*NO COMPANY*",
        "Username": "admin",
        "Password": "",
        "PasswordChanged": false,
        "flagged": false
    },
    "Device 97": {
        "Company": "*NO COMPANY*",
        "Username": "admin",
        "Password": "",
        "PasswordChanged": false,
        "flagged": false
    },
    "Device 98": {
        "Company": "*NO COMPANY*",
        "Username": "admin",
        "Password": "",
        "PasswordChanged": false,
        "flagged": false
    },
    "Device 99": {
        "Company": "*NO COMPANY*",
        "Username": "admin",
        "Password": "",
        "PasswordChanged": false,
        "flagged": false
    }
}